Workbook
Name proyAnterior: #REF!

Sheet dummys
A1: id | B1: nombres | C1: Division | D1: grupos | E1: Grupo | F1: Subgrupo | G1: Clase | H1: Subclase | I1: Articulo | J1: Subyacente | K1: NoSubyacente | L1: Transables | M1: NoTransables | N1: Bienes | O1: Servicios | P1: Alimentos | Q1: Transporte | R1: Vivienda | S1: Resto | T1: Nuevos | U1: codigo_articulo | V1: posicion | W1: PonderacionIPC
A2: 01 | B2: Alimentos y Bebidas No Alcohólicas | C2: Grupo | D2: Alimentos y Bebidas No Alcohólicas | E2: 1 | F2: 0 | G2: 0 | H2: 0 | I2: 0 | J2: 0 | K2: =IF(I2=1,IF(J2=1,0,1),0) -> 0 | L2: 0 | M2: =IF(I2=1,IF(L2=1,0,1),0) -> 0 | N2: 0 | O2: =IF(I2=1,IF(N2=1,0,1),0) -> 0 | P2: 0 | Q2: 0 | R2: 0 | S2: 0 | T2: 0 | V2: 3 | W2: 23.835128
A3: 011 | B3: Alimentos | C3: Subgrupo | D3: Alimentos y Bebidas No Alcohólicas | E3: 0 | F3: 1 | G3: 0 | H3: 0 | I3: 0 | J3: 0 | K3: =IF(I3=1,IF(J3=1,0,1),0) -> 0 | L3: 0 | M3: =IF(I3=1,IF(L3=1,0,1),0) -> 0 | N3: 0 | O3: =IF(I3=1,IF(N3=1,0,1),0) -> 0 | P3: 0 | Q3: 0 | R3: 0 | S3: 0 | T3: 0 | V3: 4 | W3: 21.043777
A4: 0111 | B4: Pan y cereales | C4: Clase | D4: Alimentos y Bebidas No Alcohólicas | E4: 0 | F4: 0 | G4: 1 | H4: 0 | I4: 0 | J4: 0 | K4: =IF(I4=1,IF(J4=1,0,1),0) -> 0 | L4: 0 | M4: =IF(I4=1,IF(L4=1,0,1),0) -> 0 | N4: 0 | O4: =IF(I4=1,IF(N4=1,0,1),0) -> 0 | P4: 0 | Q4: 0 | R4: 0 | S4: 0 | T4: 0 | V4: 5 | W4: 3.7578868
A5: 01111 | B5: Pan | C5: SubClase | D5: Alimentos y Bebidas No Alcohólicas | E5: 0 | F5: 0 | G5: 0 | H5: 1 | I5: 0 | J5: 0 | K5: =IF(I5=1,IF(J5=1,0,1),0) -> 0 | L5: 0 | M5: =IF(I5=1,IF(L5=1,0,1),0) -> 0 | N5: 0 | O5: =IF(I5=1,IF(N5=1,0,1),0) -> 0 | P5: 0 | Q5: 0 | R5: 0 | S5: 0 | T5: 0 | V5: 6 | W5: 0.94491769
A6: 0111101 | B6: Pan sobado | C6: Articulo | D6: Alimentos y Bebidas No Alcohólicas | E6: 0 | F6: 0 | G6: 0 | H6: 0 | I6: 1 | J6: 1 | K6: =IF(I6=1,IF(J6=1,0,1),0) -> 0 | L6: 0 | M6: =IF(I6=1,IF(L6=1,0,1),0) -> 1 | N6: 1 | O6: =IF(I6=1,IF(N6=1,0,1),0) -> 0 | P6: 1 | Q6: 0 | R6: 0 | S6: 0 | T6: 0 | U6: IPC_001 | V6: 7 | W6: 0.50544517
A7: 0111102 | B7: Pan de agua | C7: Articulo | D7: Alimentos y Bebidas No Alcohólicas | E7: 0 | F7: 0 | G7: 0 | H7: 0 | I7: 1 | J7: 1 | K7: =IF(I7=1,IF(J7=1,0,1),0) -> 0 | L7: 0 | M7: =IF(I7=1,IF(L7=1,0,1),0) -> 1 | N7: 1 | O7: =IF(I7=1,IF(N7=1,0,1),0) -> 0 | P7: 1 | Q7: 0 | R7: 0 | S7: 0 | T7: 0 | U7: IPC_002 | V7: 8 | W7: 0.39901799
A8: 0111104 | B8: Pan Integral | C8: Articulo | D8: Alimentos y Bebidas No Alcohólicas | E8: 0 | F8: 0 | G8: 0 | H8: 0 | I8: 1 | J8: 1 | K8: =IF(I8=1,IF(J8=1,0,1),0) -> 0 | L8: 1 | M8: =IF(I8=1,IF(L8=1,0,1),0) -> 0 | N8: 1 | O8: =IF(I8=1,IF(N8=1,0,1),0) -> 0 | P8: 1 | Q8: 0 | R8: 0 | S8: 0 | T8: 1 | U8: IPC_003 | V8: 9 | W8: 0.040454533
A9: 01112 | B9: Galletas y productos de panadería | C9: SubClase | D9: Alimentos y Bebidas No Alcohólicas | E9: 0 | F9: 0 | G9: 0 | H9: 1 | I9: 0 | J9: 0 | K9: =IF(I9=1,IF(J9=1,0,1),0) -> 0 | L9: 0 | M9: =IF(I9=1,IF(L9=1,0,1),0) -> 0 | N9: 0 | O9: =IF(I9=1,IF(N9=1,0,1),0) -> 0 | P9: 0 | Q9: 0 | R9: 0 | S9: 0 | T9: 0 | V9: 10 | W9: 0.37196575
A10: 0111201 | B10: Galletas saladas | C10: Articulo | D10: Alimentos y Bebidas No Alcohólicas | E10: 0 | F10: 0 | G10: 0 | H10: 0 | I10: 1 | J10: 1 | K10: =IF(I10=1,IF(J10=1,0,1),0) -> 0 | L10: 1 | M10: =IF(I10=1,IF(L10=1,0,1),0) -> 0 | N10: 1 | O10: =IF(I10=1,IF(N10=1,0,1),0) -> 0 | P10: 1 | Q10: 0 | R10: 0 | S10: 0 | T10: 0 | U10: IPC_004 | V10: 11 | W10: 0.13258761
A11: 0111202 | B11: Bizcochos | C11: Articulo | D11: Alimentos y Bebidas No Alcohólicas | E11: 0 | F11: 0 | G11: 0 | H11: 0 | I11: 1 | J11: 1 | K11: =IF(I11=1,IF(J11=1,0,1),0) -> 0 | L11: 1 | M11: =IF(I11=1,IF(L11=1,0,1),0) -> 0 | N11: 1 | O11: =IF(I11=1,IF(N11=1,0,1),0) -> 0 | P11: 1 | Q11: 0 | R11: 0 | S11: 0 | T11: 0 | U11: IPC_005 | V11: 12 | W11: 0.077885033
A12: 0111203 | B12: Galletas dulces | C12: Articulo | D12: Alimentos y Bebidas No Alcohólicas | E12: 0 | F12: 0 | G12: 0 | H12: 0 | I12: 1 | J12: 1 | K12: =IF(I12=1,IF(J12=1,0,1),0) -> 0 | L12: 1 | M12: =IF(I12=1,IF(L12=1,0,1),0) -> 0 | N12: 1 | O12: =IF(I12=1,IF(N12=1,0,1),0) -> 0 | P12: 1 | Q12: 0 | R12: 0 | S12: 0 | T12: 0 | U12: IPC_006 | V12: 13 | W12: 0.071040732
A13: 0111204 | B13: Galletas de harina | C13: Articulo | D13: Alimentos y Bebidas No Alcohólicas | E13: 0 | F13: 0 | G13: 0 | H13: 0 | I13: 1 | J13: 1 | K13: =IF(I13=1,IF(J13=1,0,1),0) -> 0 | L13: 0 | M13: =IF(I13=1,IF(L13=1,0,1),0) -> 1 | N13: 1 | O13: =IF(I13=1,IF(N13=1,0,1),0) -> 0 | P13: 1 | Q13: 0 | R13: 0 | S13: 0 | T13: 0 | U13: IPC_007 | V13: 14 | W13: 0.020645883
A14: 0111205 | B14: Galletas de soda | C14: Articulo | D14: Alimentos y Bebidas No Alcohólicas | E14: 0 | F14: 0 | G14: 0 | H14: 0 | I14: 1 | J14: 1 | K14: =IF(I14=1,IF(J14=1,0,1),0) -> 0 | L14: 1 | M14: =IF(I14=1,IF(L14=1,0,1),0) -> 0 | N14: 1 | O14: =IF(I14=1,IF(N14=1,0,1),0) -> 0 | P14: 1 | Q14: 0 | R14: 0 | S14: 0 | T14: 0 | U14: IPC_008 | V14: 15 | W14: 0.050453635
A15: 0111206 | B15: Galletas integrales | C15: Articulo | D15: Alimentos y Bebidas No Alcohólicas | E15: 0 | F15: 0 | G15: 0 | H15: 0 | I15: 1 | J15: 1 | K15: =IF(I15=1,IF(J15=1,0,1),0) -> 0 | L15: 1 | M15: =IF(I15=1,IF(L15=1,0,1),0) -> 0 | N15: 1 | O15: =IF(I15=1,IF(N15=1,0,1),0) -> 0 | P15: 1 | Q15: 0 | R15: 0 | S15: 0 | T15: 1 | U15: IPC_009 | V15: 16 | W15: 0.019352848
A16: 01113 | B16: Cereales y harinas | C16: SubClase | D16: Alimentos y Bebidas No Alcohólicas | E16: 0 | F16: 0 | G16: 0 | H16: 1 | I16: 0 | J16: 0 | K16: =IF(I16=1,IF(J16=1,0,1),0) -> 0 | L16: 0 | M16: =IF(I16=1,IF(L16=1,0,1),0) -> 0 | N16: 0 | O16: =IF(I16=1,IF(N16=1,0,1),0) -> 0 | P16: 0 | Q16: 0 | R16: 0 | S16: 0 | T16: 0 | V16: 17 | W16: 0.29698676
A17: 0111301 | B17: Corn Flakes | C17: Articulo | D17: Alimentos y Bebidas No Alcohólicas | E17: 0 | F17: 0 | G17: 0 | H17: 0 | I17: 1 | J17: 1 | K17: =IF(I17=1,IF(J17=1,0,1),0) -> 0 | L17: 1 | M17: =IF(I17=1,IF(L17=1,0,1),0) -> 0 | N17: 1 | O17: =IF(I17=1,IF(N17=1,0,1),0) -> 0 | P17: 1 | Q17: 0 | R17: 0 | S17: 0 | T17: 0 | U17: IPC_010 | V17: 18 | W17: 0.10689881
A18: 0111302 | B18: Avena | C18: Articulo | D18: Alimentos y Bebidas No Alcohólicas | E18: 0 | F18: 0 | G18: 0 | H18: 0 | I18: 1 | J18: 1 | K18: =IF(I18=1,IF(J18=1,0,1),0) -> 0 | L18: 1 | M18: =IF(I18=1,IF(L18=1,0,1),0) -> 0 | N18: 1 | O18: =IF(I18=1,IF(N18=1,0,1),0) -> 0 | P18: 1 | Q18: 0 | R18: 0 | S18: 0 | T18: 0 | U18: IPC_011 | V18: 19 | W18: 0.071995783
A19: 0111303 | B19: Harina de maíz | C19: Articulo | D19: Alimentos y Bebidas No Alcohólicas | E19: 0 | F19: 0 | G19: 0 | H19: 0 | I19: 1 | J19: 1 | K19: =IF(I19=1,IF(J19=1,0,1),0) -> 0 | L19: 1 | M19: =IF(I19=1,IF(L19=1,0,1),0) -> 0 | N19: 1 | O19: =IF(I19=1,IF(N19=1,0,1),0) -> 0 | P19: 1 | Q19: 0 | R19: 0 | S19: 0 | T19: 0 | U19: IPC_012 | V19: 20 | W19: 0.043458139
A20: 0111304 | B20: Harina de trigo | C20: Articulo | D20: Alimentos y Bebidas No Alcohólicas | E20: 0 | F20: 0 | G20: 0 | H20: 0 | I20: 1 | J20: 1 | K20: =IF(I20=1,IF(J20=1,0,1),0) -> 0 | L20: 1 | M20: =IF(I20=1,IF(L20=1,0,1),0) -> 0 | N20: 1 | O20: =IF(I20=1,IF(N20=1,0,1),0) -> 0 | P20: 1 | Q20: 0 | R20: 0 | S20: 0 | T20: 0 | U20: IPC_013 | V20: 21 | W20: 0.053838891
A21: 0111305 | B21: Cereales envasados | C21: Articulo | D21: Alimentos y Bebidas No Alcohólicas | E21: 0 | F21: 0 | G21: 0 | H21: 0 | I21: 1 | J21: 1 | K21: =IF(I21=1,IF(J21=1,0,1),0) -> 0 | L21: 1 | M21: =IF(I21=1,IF(L21=1,0,1),0) -> 0 | N21: 1 | O21: =IF(I21=1,IF(N21=1,0,1),0) -> 0 | P21: 1 | Q21: 0 | R21: 0 | S21: 0 | T21: 1 | U21: IPC_014 | V21: 22 | W21: 0.020795139
A22: 01114 | B22: Arroz | C22: SubClase | D22: Alimentos y Bebidas No Alcohólicas | E22: 0 | F22: 0 | G22: 0 | H22: 1 | I22: 0 | J22: 0 | K22: =IF(I22=1,IF(J22=1,0,1),0) -> 0 | L22: 0 | M22: =IF(I22=1,IF(L22=1,0,1),0) -> 0 | N22: 0 | O22: =IF(I22=1,IF(N22=1,0,1),0) -> 0 | P22: 0 | Q22: 0 | R22: 0 | S22: 0 | T22: 0 | V22: 23 | W22: 1.9448329
A23: 0111401 | B23: Arroz | C23: Articulo | D23: Alimentos y Bebidas No Alcohólicas | E23: 0 | F23: 0 | G23: 0 | H23: 0 | I23: 1 | J23: 0 | K23: =IF(I23=1,IF(J23=1,0,1),0) -> 1 | L23: 0 | M23: =IF(I23=1,IF(L23=1,0,1),0) -> 1 | N23: 1 | O23: =IF(I23=1,IF(N23=1,0,1),0) -> 0 | P23: 1 | Q23: 0 | R23: 0 | S23: 0 | T23: 0 | U23: IPC_015 | V23: 24 | W23: 1.9448329
A24: 01115 | B24: Pastas alimenticias | C24: SubClase | D24: Alimentos y Bebidas No Alcohólicas | E24: 0 | F24: 0 | G24: 0 | H24: 1 | I24: 0 | J24: 0 | K24: =IF(I24=1,IF(J24=1,0,1),0) -> 0 | L24: 0 | M24: =IF(I24=1,IF(L24=1,0,1),0) -> 0 | N24: 0 | O24: =IF(I24=1,IF(N24=1,0,1),0) -> 0 | P24: 0 | Q24: 0 | R24: 0 | S24: 0 | T24: 0 | V24: 25 | W24: 0.19918367
A25: 0111501 | B25: Spaghetti | C25: Articulo | D25: Alimentos y Bebidas No Alcohólicas | E25: 0 | F25: 0 | G25: 0 | H25: 0 | I25: 1 | J25: 1 | K25: =IF(I25=1,IF(J25=1,0,1),0) -> 0 | L25: 1 | M25: =IF(I25=1,IF(L25=1,0,1),0) -> 0 | N25: 1 | O25: =IF(I25=1,IF(N25=1,0,1),0) -> 0 | P25: 1 | Q25: 0 | R25: 0 | S25: 0 | T25: 0 | U25: IPC_016 | V25: 26 | W25: 0.11647762
A26: 0111502 | B26: Fideos | C26: Articulo | D26: Alimentos y Bebidas No Alcohólicas | E26: 0 | F26: 0 | G26: 0 | H26: 0 | I26: 1 | J26: 1 | K26: =IF(I26=1,IF(J26=1,0,1),0) -> 0 | L26: 1 | M26: =IF(I26=1,IF(L26=1,0,1),0) -> 0 | N26: 1 | O26: =IF(I26=1,IF(N26=1,0,1),0) -> 0 | P26: 1 | Q26: 0 | R26: 0 | S26: 0 | T26: 0 | U26: IPC_017 | V26: 27 | W26: 0.051966374
A27: 0111503 | B27: Pastas cortas | C27: Articulo | D27: Alimentos y Bebidas No Alcohólicas | E27: 0 | F27: 0 | G27: 0 | H27: 0 | I27: 1 | J27: 1 | K27: =IF(I27=1,IF(J27=1,0,1),0) -> 0 | L27: 1 | M27: =IF(I27=1,IF(L27=1,0,1),0) -> 0 | N27: 1 | O27: =IF(I27=1,IF(N27=1,0,1),0) -> 0 | P27: 1 | Q27: 0 | R27: 0 | S27: 0 | T27: 1 | U27: IPC_018 | V27: 28 | W27: 0.030739679
A28: 0112 | B28: Carnes | C28: Clase | D28: Alimentos y Bebidas No Alcohólicas | E28: 0 | F28: 0 | G28: 1 | H28: 0 | I28: 0 | J28: 0 | K28: =IF(I28=1,IF(J28=1,0,1),0) -> 0 | L28: 0 | M28: =IF(I28=1,IF(L28=1,0,1),0) -> 0 | N28: 0 | O28: =IF(I28=1,IF(N28=1,0,1),0) -> 0 | P28: 0 | Q28: 0 | R28: 0 | S28: 0 | T28: 0 | V28: 29 | W28: 5.2990782
A29: 01121 | B29: Carne de res | C29: SubClase | D29: Alimentos y Bebidas No Alcohólicas | E29: 0 | F29: 0 | G29: 0 | H29: 1 | I29: 0 | J29: 0 | K29: =IF(I29=1,IF(J29=1,0,1),0) -> 0 | L29: 0 | M29: =IF(I29=1,IF(L29=1,0,1),0) -> 0 | N29: 0 | O29: =IF(I29=1,IF(N29=1,0,1),0) -> 0 | P29: 0 | Q29: 0 | R29: 0 | S29: 0 | T29: 0 | V29: 30 | W29: 0.57658004
A30: 0112101 | B30: Carne corriente de res | C30: Articulo | D30: Alimentos y Bebidas No Alcohólicas | E30: 0 | F30: 0 | G30: 0 | H30: 0 | I30: 1 | J30: 1 | K30: =IF(I30=1,IF(J30=1,0,1),0) -> 0 | L30: 1 | M30: =IF(I30=1,IF(L30=1,0,1),0) -> 0 | N30: 1 | O30: =IF(I30=1,IF(N30=1,0,1),0) -> 0 | P30: 1 | Q30: 0 | R30: 0 | S30: 0 | T30: 0 | U30: IPC_019 | V30: 31 | W30: 0.45328811
A31: 0112102 | B31: Carne de bola | C31: Articulo | D31: Alimentos y Bebidas No Alcohólicas | E31: 0 | F31: 0 | G31: 0 | H31: 0 | I31: 1 | J31: 1 | K31: =IF(I31=1,IF(J31=1,0,1),0) -> 0 | L31: 1 | M31: =IF(I31=1,IF(L31=1,0,1),0) -> 0 | N31: 1 | O31: =IF(I31=1,IF(N31=1,0,1),0) -> 0 | P31: 1 | Q31: 0 | R31: 0 | S31: 0 | T31: 0 | U31: IPC_020 | V31: 32 | W31: 0.028030455
A32: 0112103 | B32: Carne molida de res | C32: Articulo | D32: Alimentos y Bebidas No Alcohólicas | E32: 0 | F32: 0 | G32: 0 | H32: 0 | I32: 1 | J32: 1 | K32: =IF(I32=1,IF(J32=1,0,1),0) -> 0 | L32: 1 | M32: =IF(I32=1,IF(L32=1,0,1),0) -> 0 | N32: 1 | O32: =IF(I32=1,IF(N32=1,0,1),0) -> 0 | P32: 1 | Q32: 0 | R32: 0 | S32: 0 | T32: 0 | U32: IPC_021 | V32: 33 | W32: 0.095261474
A33: 01122 | B33: Carne de aves | C33: SubClase | D33: Alimentos y Bebidas No Alcohólicas | E33: 0 | F33: 0 | G33: 0 | H33: 1 | I33: 0 | J33: 0 | K33: =IF(I33=1,IF(J33=1,0,1),0) -> 0 | L33: 0 | M33: =IF(I33=1,IF(L33=1,0,1),0) -> 0 | N33: 0 | O33: =IF(I33=1,IF(N33=1,0,1),0) -> 0 | P33: 0 | Q33: 0 | R33: 0 | S33: 0 | T33: 0 | V33: 34 | W33: 2.4568069
A34: 0112201 | B34: Pollo fresco | C34: Articulo | D34: Alimentos y Bebidas No Alcohólicas | E34: 0 | F34: 0 | G34: 0 | H34: 0 | I34: 1 | J34: 0 | K34: =IF(I34=1,IF(J34=1,0,1),0) -> 1 | L34: 0 | M34: =IF(I34=1,IF(L34=1,0,1),0) -> 1 | N34: 1 | O34: =IF(I34=1,IF(N34=1,0,1),0) -> 0 | P34: 1 | Q34: 0 | R34: 0 | S34: 0 | T34: 0 | U34: IPC_022 | V34: 35 | W34: 2.3299065
A35: 0112202 | B35: Carne de gallina | C35: Articulo | D35: Alimentos y Bebidas No Alcohólicas | E35: 0 | F35: 0 | G35: 0 | H35: 0 | I35: 1 | J35: 0 | K35: =IF(I35=1,IF(J35=1,0,1),0) -> 1 | L35: 0 | M35: =IF(I35=1,IF(L35=1,0,1),0) -> 1 | N35: 1 | O35: =IF(I35=1,IF(N35=1,0,1),0) -> 0 | P35: 1 | Q35: 0 | R35: 0 | S35: 0 | T35: 0 | U35: IPC_023 | V35: 36 | W35: 0.059928253
A36: 0112203 | B36: Pechuga de pollo | C36: Articulo | D36: Alimentos y Bebidas No Alcohólicas | E36: 0 | F36: 0 | G36: 0 | H36: 0 | I36: 1 | J36: 0 | K36: =IF(I36=1,IF(J36=1,0,1),0) -> 1 | L36: 0 | M36: =IF(I36=1,IF(L36=1,0,1),0) -> 1 | N36: 1 | O36: =IF(I36=1,IF(N36=1,0,1),0) -> 0 | P36: 1 | Q36: 0 | R36: 0 | S36: 0 | T36: 1 | U36: IPC_024 | V36: 37 | W36: 0.066972124
A37: 01123 | B37: Carne de cerdo | C37: SubClase | D37: Alimentos y Bebidas No Alcohólicas | E37: 0 | F37: 0 | G37: 0 | H37: 1 | I37: 0 | J37: 0 | K37: =IF(I37=1,IF(J37=1,0,1),0) -> 0 | L37: 0 | M37: =IF(I37=1,IF(L37=1,0,1),0) -> 0 | N37: 0 | O37: =IF(I37=1,IF(N37=1,0,1),0) -> 0 | P37: 0 | Q37: 0 | R37: 0 | S37: 0 | T37: 0 | V37: 38 | W37: 0.58121541
A38: 0112301 | B38: Carne corriente de cerdo | C38: Articulo | D38: Alimentos y Bebidas No Alcohólicas | E38: 0 | F38: 0 | G38: 0 | H38: 0 | I38: 1 | J38: 1 | K38: =IF(I38=1,IF(J38=1,0,1),0) -> 0 | L38: 1 | M38: =IF(I38=1,IF(L38=1,0,1),0) -> 0 | N38: 1 | O38: =IF(I38=1,IF(N38=1,0,1),0) -> 0 | P38: 1 | Q38: 0 | R38: 0 | S38: 0 | T38: 0 | U38: IPC_025 | V38: 39 | W38: 0.47122464
A39: 0112302 | B39: Chuleta de cerdo | C39: Articulo | D39: Alimentos y Bebidas No Alcohólicas | E39: 0 | F39: 0 | G39: 0 | H39: 0 | I39: 1 | J39: 1 | K39: =IF(I39=1,IF(J39=1,0,1),0) -> 0 | L39: 1 | M39: =IF(I39=1,IF(L39=1,0,1),0) -> 0 | N39: 1 | O39: =IF(I39=1,IF(N39=1,0,1),0) -> 0 | P39: 1 | Q39: 0 | R39: 0 | S39: 0 | T39: 0 | U39: IPC_026 | V39: 40 | W39: 0.033001269
A40: 0112304 | B40: Pierna de cerdo | C40: Articulo | D40: Alimentos y Bebidas No Alcohólicas | E40: 0 | F40: 0 | G40: 0 | H40: 0 | I40: 1 | J40: 1 | K40: =IF(I40=1,IF(J40=1,0,1),0) -> 0 | L40: 1 | M40: =IF(I40=1,IF(L40=1,0,1),0) -> 0 | N40: 1 | O40: =IF(I40=1,IF(N40=1,0,1),0) -> 0 | P40: 1 | Q40: 0 | R40: 0 | S40: 0 | T40: 1 | U40: IPC_027 | V40: 41 | W40: 0.044233568
A41: 0112305 | B41: Costillas de cerdo | C41: Articulo | D41: Alimentos y Bebidas No Alcohólicas | E41: 0 | F41: 0 | G41: 0 | H41: 0 | I41: 1 | J41: 1 | K41: =IF(I41=1,IF(J41=1,0,1),0) -> 0 | L41: 1 | M41: =IF(I41=1,IF(L41=1,0,1),0) -> 0 | N41: 1 | O41: =IF(I41=1,IF(N41=1,0,1),0) -> 0 | P41: 1 | Q41: 0 | R41: 0 | S41: 0 | T41: 1 | U41: IPC_028 | V41: 42 | W41: 0.032755937
A42: 01124 | B42: Otras carnes | C42: SubClase | D42: Alimentos y Bebidas No Alcohólicas | E42: 0 | F42: 0 | G42: 0 | H42: 1 | I42: 0 | J42: 0 | K42: =IF(I42=1,IF(J42=1,0,1),0) -> 0 | L42: 0 | M42: =IF(I42=1,IF(L42=1,0,1),0) -> 0 | N42: 0 | O42: =IF(I42=1,IF(N42=1,0,1),0) -> 0 | P42: 0 | Q42: 0 | R42: 0 | S42: 0 | T42: 0 | V42: 43 | W42: 0.092631972
A43: 0112402 | B43: Hígado de res | C43: Articulo | D43: Alimentos y Bebidas No Alcohólicas | E43: 0 | F43: 0 | G43: 0 | H43: 0 | I43: 1 | J43: 0 | K43: =IF(I43=1,IF(J43=1,0,1),0) -> 1 | L43: 0 | M43: =IF(I43=1,IF(L43=1,0,1),0) -> 1 | N43: 1 | O43: =IF(I43=1,IF(N43=1,0,1),0) -> 0 | P43: 1 | Q43: 0 | R43: 0 | S43: 0 | T43: 1 | U43: IPC_029 | V43: 44 | W43: 0.092631972
A44: 01125 | B44: Embutidos y carnes preparadas | C44: SubClase | D44: Alimentos y Bebidas No Alcohólicas | E44: 0 | F44: 0 | G44: 0 | H44: 1 | I44: 0 | J44: 0 | K44: =IF(I44=1,IF(J44=1,0,1),0) -> 0 | L44: 0 | M44: =IF(I44=1,IF(L44=1,0,1),0) -> 0 | N44: 0 | O44: =IF(I44=1,IF(N44=1,0,1),0) -> 0 | P44: 0 | Q44: 0 | R44: 0 | S44: 0 | T44: 0 | V44: 45 | W44: 1.5918439
A45: 0112501 | B45: Salami | C45: Articulo | D45: Alimentos y Bebidas No Alcohólicas | E45: 0 | F45: 0 | G45: 0 | H45: 0 | I45: 1 | J45: 1 | K45: =IF(I45=1,IF(J45=1,0,1),0) -> 0 | L45: 1 | M45: =IF(I45=1,IF(L45=1,0,1),0) -> 0 | N45: 1 | O45: =IF(I45=1,IF(N45=1,0,1),0) -> 0 | P45: 1 | Q45: 0 | R45: 0 | S45: 0 | T45: 0 | U45: IPC_030 | V45: 46 | W45: 0.75599233
A46: 0112502 | B46: Chuleta ahumada | C46: Articulo | D46: Alimentos y Bebidas No Alcohólicas | E46: 0 | F46: 0 | G46: 0 | H46: 0 | I46: 1 | J46: 1 | K46: =IF(I46=1,IF(J46=1,0,1),0) -> 0 | L46: 1 | M46: =IF(I46=1,IF(L46=1,0,1),0) -> 0 | N46: 1 | O46: =IF(I46=1,IF(N46=1,0,1),0) -> 0 | P46: 1 | Q46: 0 | R46: 0 | S46: 0 | T46: 0 | U46: IPC_031 | V46: 47 | W46: 0.43933243
A47: 0112503 | B47: Jamones | C47: Articulo | D47: Alimentos y Bebidas No Alcohólicas | E47: 0 | F47: 0 | G47: 0 | H47: 0 | I47: 1 | J47: 1 | K47: =IF(I47=1,IF(J47=1,0,1),0) -> 0 | L47: 1 | M47: =IF(I47=1,IF(L47=1,0,1),0) -> 0 | N47: 1 | O47: =IF(I47=1,IF(N47=1,0,1),0) -> 0 | P47: 1 | Q47: 0 | R47: 0 | S47: 0 | T47: 0 | U47: IPC_032 | V47: 48 | W47: 0.14082646
A48: 0112504 | B48: Longaniza | C48: Articulo | D48: Alimentos y Bebidas No Alcohólicas | E48: 0 | F48: 0 | G48: 0 | H48: 0 | I48: 1 | J48: 1 | K48: =IF(I48=1,IF(J48=1,0,1),0) -> 0 | L48: 1 | M48: =IF(I48=1,IF(L48=1,0,1),0) -> 0 | N48: 1 | O48: =IF(I48=1,IF(N48=1,0,1),0) -> 0 | P48: 1 | Q48: 0 | R48: 0 | S48: 0 | T48: 0 | U48: IPC_033 | V48: 49 | W48: 0.15542774
A49: 0112506 | B49: Salchichas | C49: Articulo | D49: Alimentos y Bebidas No Alcohólicas | E49: 0 | F49: 0 | G49: 0 | H49: 0 | I49: 1 | J49: 1 | K49: =IF(I49=1,IF(J49=1,0,1),0) -> 0 | L49: 1 | M49: =IF(I49=1,IF(L49=1,0,1),0) -> 0 | N49: 1 | O49: =IF(I49=1,IF(N49=1,0,1),0) -> 0 | P49: 1 | Q49: 0 | R49: 0 | S49: 0 | T49: 0 | U49: IPC_034 | V49: 50 | W49: 0.039453295
A50: 0112507 | B50: Costillita ahumada de cerdo | C50: Articulo | D50: Alimentos y Bebidas No Alcohólicas | E50: 0 | F50: 0 | G50: 0 | H50: 0 | I50: 1 | J50: 1 | K50: =IF(I50=1,IF(J50=1,0,1),0) -> 0 | L50: 1 | M50: =IF(I50=1,IF(L50=1,0,1),0) -> 0 | N50: 1 | O50: =IF(I50=1,IF(N50=1,0,1),0) -> 0 | P50: 1 | Q50: 0 | R50: 0 | S50: 0 | T50: 1 | U50: IPC_035 | V50: 51 | W50: 0.03370023
A51: 0112508 | B51: Jamoneta | C51: Articulo | D51: Alimentos y Bebidas No Alcohólicas | E51: 0 | F51: 0 | G51: 0 | H51: 0 | I51: 1 | J51: 1 | K51: =IF(I51=1,IF(J51=1,0,1),0) -> 0 | L51: 1 | M51: =IF(I51=1,IF(L51=1,0,1),0) -> 0 | N51: 1 | O51: =IF(I51=1,IF(N51=1,0,1),0) -> 0 | P51: 1 | Q51: 0 | R51: 0 | S51: 0 | T51: 1 | U51: IPC_036 | V51: 52 | W51: 0.027111399
A52: 0113 | B52: Pescado | C52: Clase | D52: Alimentos y Bebidas No Alcohólicas | E52: 0 | F52: 0 | G52: 1 | H52: 0 | I52: 0 | J52: 0 | K52: =IF(I52=1,IF(J52=1,0,1),0) -> 0 | L52: 0 | M52: =IF(I52=1,IF(L52=1,0,1),0) -> 0 | N52: 0 | O52: =IF(I52=1,IF(N52=1,0,1),0) -> 0 | P52: 0 | Q52: 0 | R52: 0 | S52: 0 | T52: 0 | V52: 53 | W52: 0.87925302
A53: 01131 | B53: Pescados y mariscos frescos, refrigerados y congelados | C53: SubClase | D53: Alimentos y Bebidas No Alcohólicas | E53: 0 | F53: 0 | G53: 0 | H53: 1 | I53: 0 | J53: 0 | K53: =IF(I53=1,IF(J53=1,0,1),0) -> 0 | L53: 0 | M53: =IF(I53=1,IF(L53=1,0,1),0) -> 0 | N53: 0 | O53: =IF(I53=1,IF(N53=1,0,1),0) -> 0 | P53: 0 | Q53: 0 | R53: 0 | S53: 0 | T53: 0 | V53: 54 | W53: 0.31351786
A54: 0113101 | B54: Pescado fresco y refrigerado | C54: Articulo | D54: Alimentos y Bebidas No Alcohólicas | E54: 0 | F54: 0 | G54: 0 | H54: 0 | I54: 1 | J54: 1 | K54: =IF(I54=1,IF(J54=1,0,1),0) -> 0 | L54: 1 | M54: =IF(I54=1,IF(L54=1,0,1),0) -> 0 | N54: 1 | O54: =IF(I54=1,IF(N54=1,0,1),0) -> 0 | P54: 1 | Q54: 0 | R54: 0 | S54: 0 | T54: 0 | U54: IPC_037 | V54: 55 | W54: 0.17965504
A55: 0113102 | B55: Camarones | C55: Articulo | D55: Alimentos y Bebidas No Alcohólicas | E55: 0 | F55: 0 | G55: 0 | H55: 0 | I55: 1 | J55: 1 | K55: =IF(I55=1,IF(J55=1,0,1),0) -> 0 | L55: 1 | M55: =IF(I55=1,IF(L55=1,0,1),0) -> 0 | N55: 1 | O55: =IF(I55=1,IF(N55=1,0,1),0) -> 0 | P55: 1 | Q55: 0 | R55: 0 | S55: 0 | T55: 0 | U55: IPC_038 | V55: 56 | W55: 0.03497932
A56: 0113103 | B56: Tilapia | C56: Articulo | D56: Alimentos y Bebidas No Alcohólicas | E56: 0 | F56: 0 | G56: 0 | H56: 0 | I56: 1 | J56: 1 | K56: =IF(I56=1,IF(J56=1,0,1),0) -> 0 | L56: 1 | M56: =IF(I56=1,IF(L56=1,0,1),0) -> 0 | N56: 1 | O56: =IF(I56=1,IF(N56=1,0,1),0) -> 0 | P56: 1 | Q56: 0 | R56: 0 | S56: 0 | T56: 0 | U56: IPC_039 | V56: 57 | W56: 0.098883499
A57: 01132 | B57: Pescados procesados y en conserva | C57: SubClase | D57: Alimentos y Bebidas No Alcohólicas | E57: 0 | F57: 0 | G57: 0 | H57: 1 | I57: 0 | J57: 0 | K57: =IF(I57=1,IF(J57=1,0,1),0) -> 0 | L57: 0 | M57: =IF(I57=1,IF(L57=1,0,1),0) -> 0 | N57: 0 | O57: =IF(I57=1,IF(N57=1,0,1),0) -> 0 | P57: 0 | Q57: 0 | R57: 0 | S57: 0 | T57: 0 | V57: 58 | W57: 0.56573517
A58: 0113201 | B58: Bacalao | C58: Articulo | D58: Alimentos y Bebidas No Alcohólicas | E58: 0 | F58: 0 | G58: 0 | H58: 0 | I58: 1 | J58: 1 | K58: =IF(I58=1,IF(J58=1,0,1),0) -> 0 | L58: 1 | M58: =IF(I58=1,IF(L58=1,0,1),0) -> 0 | N58: 1 | O58: =IF(I58=1,IF(N58=1,0,1),0) -> 0 | P58: 1 | Q58: 0 | R58: 0 | S58: 0 | T58: 0 | U58: IPC_040 | V58: 59 | W58: 0.27685189
A59: 0113202 | B59: Sardinas | C59: Articulo | D59: Alimentos y Bebidas No Alcohólicas | E59: 0 | F59: 0 | G59: 0 | H59: 0 | I59: 1 | J59: 1 | K59: =IF(I59=1,IF(J59=1,0,1),0) -> 0 | L59: 1 | M59: =IF(I59=1,IF(L59=1,0,1),0) -> 0 | N59: 1 | O59: =IF(I59=1,IF(N59=1,0,1),0) -> 0 | P59: 1 | Q59: 0 | R59: 0 | S59: 0 | T59: 0 | U59: IPC_041 | V59: 60 | W59: 0.16085442
A60: 0113203 | B60: Arenque | C60: Articulo | D60: Alimentos y Bebidas No Alcohólicas | E60: 0 | F60: 0 | G60: 0 | H60: 0 | I60: 1 | J60: 1 | K60: =IF(I60=1,IF(J60=1,0,1),0) -> 0 | L60: 1 | M60: =IF(I60=1,IF(L60=1,0,1),0) -> 0 | N60: 1 | O60: =IF(I60=1,IF(N60=1,0,1),0) -> 0 | P60: 1 | Q60: 0 | R60: 0 | S60: 0 | T60: 0 | U60: IPC_042 | V60: 61 | W60: 0.064417184
A61: 0113204 | B61: Atún | C61: Articulo | D61: Alimentos y Bebidas No Alcohólicas | E61: 0 | F61: 0 | G61: 0 | H61: 0 | I61: 1 | J61: 1 | K61: =IF(I61=1,IF(J61=1,0,1),0) -> 0 | L61: 1 | M61: =IF(I61=1,IF(L61=1,0,1),0) -> 0 | N61: 1 | O61: =IF(I61=1,IF(N61=1,0,1),0) -> 0 | P61: 1 | Q61: 0 | R61: 0 | S61: 0 | T61: 0 | U61: IPC_043 | V61: 62 | W61: 0.063611677
A62: 0114 | B62: Leche, queso y huevos | C62: Clase | D62: Alimentos y Bebidas No Alcohólicas | E62: 0 | F62: 0 | G62: 1 | H62: 0 | I62: 0 | J62: 0 | K62: =IF(I62=1,IF(J62=1,0,1),0) -> 0 | L62: 0 | M62: =IF(I62=1,IF(L62=1,0,1),0) -> 0 | N62: 0 | O62: =IF(I62=1,IF(N62=1,0,1),0) -> 0 | P62: 0 | Q62: 0 | R62: 0 | S62: 0 | T62: 0 | V62: 63 | W62: 2.9905282
A63: 01141 | B63: Leche | C63: SubClase | D63: Alimentos y Bebidas No Alcohólicas | E63: 0 | F63: 0 | G63: 0 | H63: 1 | I63: 0 | J63: 0 | K63: =IF(I63=1,IF(J63=1,0,1),0) -> 0 | L63: 0 | M63: =IF(I63=1,IF(L63=1,0,1),0) -> 0 | N63: 0 | O63: =IF(I63=1,IF(N63=1,0,1),0) -> 0 | P63: 0 | Q63: 0 | R63: 0 | S63: 0 | T63: 0 | V63: 64 | W63: 1.4923501
A64: 0114101 | B64: Leche en polvo | C64: Articulo | D64: Alimentos y Bebidas No Alcohólicas | E64: 0 | F64: 0 | G64: 0 | H64: 0 | I64: 1 | J64: 1 | K64: =IF(I64=1,IF(J64=1,0,1),0) -> 0 | L64: 0 | M64: =IF(I64=1,IF(L64=1,0,1),0) -> 1 | N64: 1 | O64: =IF(I64=1,IF(N64=1,0,1),0) -> 0 | P64: 1 | Q64: 0 | R64: 0 | S64: 0 | T64: 0 | U64: IPC_044 | V64: 65 | W64: 0.25734548
A65: 0114102 | B65: Leche evaporada | C65: Articulo | D65: Alimentos y Bebidas No Alcohólicas | E65: 0 | F65: 0 | G65: 0 | H65: 0 | I65: 1 | J65: 1 | K65: =IF(I65=1,IF(J65=1,0,1),0) -> 0 | L65: 1 | M65: =IF(I65=1,IF(L65=1,0,1),0) -> 0 | N65: 1 | O65: =IF(I65=1,IF(N65=1,0,1),0) -> 0 | P65: 1 | Q65: 0 | R65: 0 | S65: 0 | T65: 0 | U65: IPC_045 | V65: 66 | W65: 0.30439867
A66: 0114103 | B66: Leche líquida | C66: Articulo | D66: Alimentos y Bebidas No Alcohólicas | E66: 0 | F66: 0 | G66: 0 | H66: 0 | I66: 1 | J66: 1 | K66: =IF(I66=1,IF(J66=1,0,1),0) -> 0 | L66: 0 | M66: =IF(I66=1,IF(L66=1,0,1),0) -> 1 | N66: 1 | O66: =IF(I66=1,IF(N66=1,0,1),0) -> 0 | P66: 1 | Q66: 0 | R66: 0 | S66: 0 | T66: 0 | U66: IPC_046 | V66: 67 | W66: 0.55595534
A67: 0114104 | B67: Leche maternizada | C67: Articulo | D67: Alimentos y Bebidas No Alcohólicas | E67: 0 | F67: 0 | G67: 0 | H67: 0 | I67: 1 | J67: 1 | K67: =IF(I67=1,IF(J67=1,0,1),0) -> 0 | L67: 1 | M67: =IF(I67=1,IF(L67=1,0,1),0) -> 0 | N67: 1 | O67: =IF(I67=1,IF(N67=1,0,1),0) -> 0 | P67: 1 | Q67: 0 | R67: 0 | S67: 0 | T67: 1 | U67: IPC_047 | V67: 68 | W67: 0.061261991
A68: 0114105 | B68: Suplementos alimenticios | C68: Articulo | D68: Alimentos y Bebidas No Alcohólicas | E68: 0 | F68: 0 | G68: 0 | H68: 0 | I68: 1 | J68: 1 | K68: =IF(I68=1,IF(J68=1,0,1),0) -> 0 | L68: 1 | M68: =IF(I68=1,IF(L68=1,0,1),0) -> 0 | N68: 1 | O68: =IF(I68=1,IF(N68=1,0,1),0) -> 0 | P68: 1 | Q68: 0 | R68: 0 | S68: 0 | T68: 1 | U68: IPC_048 | V68: 69 | W68: 0.050276757
A69: 0114106 | B69: Leche de origen vegetal | C69: Articulo | D69: Alimentos y Bebidas No Alcohólicas | E69: 0 | F69: 0 | G69: 0 | H69: 0 | I69: 1 | J69: 1 | K69: =IF(I69=1,IF(J69=1,0,1),0) -> 0 | L69: 1 | M69: =IF(I69=1,IF(L69=1,0,1),0) -> 0 | N69: 1 | O69: =IF(I69=1,IF(N69=1,0,1),0) -> 0 | P69: 1 | Q69: 0 | R69: 0 | S69: 0 | T69: 1 | U69: IPC_049 | V69: 70 | W69: 0.030711221
A70: 0114107 | B70: Leche saborizada | C70: Articulo | D70: Alimentos y Bebidas No Alcohólicas | E70: 0 | F70: 0 | G70: 0 | H70: 0 | I70: 1 | J70: 1 | K70: =IF(I70=1,IF(J70=1,0,1),0) -> 0 | L70: 1 | M70: =IF(I70=1,IF(L70=1,0,1),0) -> 0 | N70: 1 | O70: =IF(I70=1,IF(N70=1,0,1),0) -> 0 | P70: 1 | Q70: 0 | R70: 0 | S70: 0 | T70: 1 | U70: IPC_050 | V70: 71 | W70: 0.048787669
A71: 0114108 | B71: Leche reforzada | C71: Articulo | D71: Alimentos y Bebidas No Alcohólicas | E71: 0 | F71: 0 | G71: 0 | H71: 0 | I71: 1 | J71: 1 | K71: =IF(I71=1,IF(J71=1,0,1),0) -> 0 | L71: 1 | M71: =IF(I71=1,IF(L71=1,0,1),0) -> 0 | N71: 1 | O71: =IF(I71=1,IF(N71=1,0,1),0) -> 0 | P71: 1 | Q71: 0 | R71: 0 | S71: 0 | T71: 1 | U71: IPC_051 | V71: 72 | W71: 0.18361292
A72: 01142 | B72: Quesos | C72: SubClase | D72: Alimentos y Bebidas No Alcohólicas | E72: 0 | F72: 0 | G72: 0 | H72: 1 | I72: 0 | J72: 0 | K72: =IF(I72=1,IF(J72=1,0,1),0) -> 0 | L72: 0 | M72: =IF(I72=1,IF(L72=1,0,1),0) -> 0 | N72: 0 | O72: =IF(I72=1,IF(N72=1,0,1),0) -> 0 | P72: 0 | Q72: 0 | R72: 0 | S72: 0 | T72: 0 | V72: 73 | W72: 0.81528031
A73: 0114201 | B73: Queso blanco | C73: Articulo | D73: Alimentos y Bebidas No Alcohólicas | E73: 0 | F73: 0 | G73: 0 | H73: 0 | I73: 1 | J73: 1 | K73: =IF(I73=1,IF(J73=1,0,1),0) -> 0 | L73: 1 | M73: =IF(I73=1,IF(L73=1,0,1),0) -> 0 | N73: 1 | O73: =IF(I73=1,IF(N73=1,0,1),0) -> 0 | P73: 1 | Q73: 0 | R73: 0 | S73: 0 | T73: 0 | U73: IPC_052 | V73: 74 | W73: 0.32377267
A74: 0114202 | B74: Queso cheddar amarillo | C74: Articulo | D74: Alimentos y Bebidas No Alcohólicas | E74: 0 | F74: 0 | G74: 0 | H74: 0 | I74: 1 | J74: 1 | K74: =IF(I74=1,IF(J74=1,0,1),0) -> 0 | L74: 1 | M74: =IF(I74=1,IF(L74=1,0,1),0) -> 0 | N74: 1 | O74: =IF(I74=1,IF(N74=1,0,1),0) -> 0 | P74: 1 | Q74: 0 | R74: 0 | S74: 0 | T74: 0 | U74: IPC_053 | V74: 75 | W74: 0.25760396
A75: 0114203 | B75: Queso holandés | C75: Articulo | D75: Alimentos y Bebidas No Alcohólicas | E75: 0 | F75: 0 | G75: 0 | H75: 0 | I75: 1 | J75: 1 | K75: =IF(I75=1,IF(J75=1,0,1),0) -> 0 | L75: 1 | M75: =IF(I75=1,IF(L75=1,0,1),0) -> 0 | N75: 1 | O75: =IF(I75=1,IF(N75=1,0,1),0) -> 0 | P75: 1 | Q75: 0 | R75: 0 | S75: 0 | T75: 0 | U75: IPC_054 | V75: 76 | W75: 0.11986205
A76: 0114204 | B76: Otros Quesos (Mozarella, Danes) | C76: Articulo | D76: Alimentos y Bebidas No Alcohólicas | E76: 0 | F76: 0 | G76: 0 | H76: 0 | I76: 1 | J76: 1 | K76: =IF(I76=1,IF(J76=1,0,1),0) -> 0 | L76: 1 | M76: =IF(I76=1,IF(L76=1,0,1),0) -> 0 | N76: 1 | O76: =IF(I76=1,IF(N76=1,0,1),0) -> 0 | P76: 1 | Q76: 0 | R76: 0 | S76: 0 | T76: 1 | U76: IPC_055 | V76: 77 | W76: 0.050925217
A77: 0114205 | B77: Queso de hoja | C77: Articulo | D77: Alimentos y Bebidas No Alcohólicas | E77: 0 | F77: 0 | G77: 0 | H77: 0 | I77: 1 | J77: 1 | K77: =IF(I77=1,IF(J77=1,0,1),0) -> 0 | L77: 1 | M77: =IF(I77=1,IF(L77=1,0,1),0) -> 0 | N77: 1 | O77: =IF(I77=1,IF(N77=1,0,1),0) -> 0 | P77: 1 | Q77: 0 | R77: 0 | S77: 0 | T77: 1 | U77: IPC_056 | V77: 78 | W77: 0.063116407
A78: 01143 | B78: Yogurt y otros productos lácteos | C78: SubClase | D78: Alimentos y Bebidas No Alcohólicas | E78: 0 | F78: 0 | G78: 0 | H78: 1 | I78: 0 | J78: 0 | K78: =IF(I78=1,IF(J78=1,0,1),0) -> 0 | L78: 0 | M78: =IF(I78=1,IF(L78=1,0,1),0) -> 0 | N78: 0 | O78: =IF(I78=1,IF(N78=1,0,1),0) -> 0 | P78: 0 | Q78: 0 | R78: 0 | S78: 0 | T78: 0 | V78: 79 | W78: 0.094443893
A79: 0114301 | B79: Yogurt | C79: Articulo | D79: Alimentos y Bebidas No Alcohólicas | E79: 0 | F79: 0 | G79: 0 | H79: 0 | I79: 1 | J79: 1 | K79: =IF(I79=1,IF(J79=1,0,1),0) -> 0 | L79: 1 | M79: =IF(I79=1,IF(L79=1,0,1),0) -> 0 | N79: 1 | O79: =IF(I79=1,IF(N79=1,0,1),0) -> 0 | P79: 1 | Q79: 0 | R79: 0 | S79: 0 | T79: 0 | U79: IPC_057 | V79: 80 | W79: 0.094443893
A80: 01144 | B80: Huevos | C80: SubClase | D80: Alimentos y Bebidas No Alcohólicas | E80: 0 | F80: 0 | G80: 0 | H80: 1 | I80: 0 | J80: 0 | K80: =IF(I80=1,IF(J80=1,0,1),0) -> 0 | L80: 0 | M80: =IF(I80=1,IF(L80=1,0,1),0) -> 0 | N80: 0 | O80: =IF(I80=1,IF(N80=1,0,1),0) -> 0 | P80: 0 | Q80: 0 | R80: 0 | S80: 0 | T80: 0 | V80: 81 | W80: 0.58845399
A81: 0114401 | B81: Huevos | C81: Articulo | D81: Alimentos y Bebidas No Alcohólicas | E81: 0 | F81: 0 | G81: 0 | H81: 0 | I81: 1 | J81: 0 | K81: =IF(I81=1,IF(J81=1,0,1),0) -> 1 | L81: 1 | M81: =IF(I81=1,IF(L81=1,0,1),0) -> 0 | N81: 1 | O81: =IF(I81=1,IF(N81=1,0,1),0) -> 0 | P81: 1 | Q81: 0 | R81: 0 | S81: 0 | T81: 0 | U81: IPC_058 | V81: 82 | W81: 0.58845399
A82: 0115 | B82: Aceites y grasas | C82: Clase | D82: Alimentos y Bebidas No Alcohólicas | E82: 0 | F82: 0 | G82: 1 | H82: 0 | I82: 0 | J82: 0 | K82: =IF(I82=1,IF(J82=1,0,1),0) -> 0 | L82: 0 | M82: =IF(I82=1,IF(L82=1,0,1),0) -> 0 | N82: 0 | O82: =IF(I82=1,IF(N82=1,0,1),0) -> 0 | P82: 0 | Q82: 0 | R82: 0 | S82: 0 | T82: 0 | V82: 83 | W82: 0.65911803
A83: 01151 | B83: Aceites | C83: SubClase | D83: Alimentos y Bebidas No Alcohólicas | E83: 0 | F83: 0 | G83: 0 | H83: 1 | I83: 0 | J83: 0 | K83: =IF(I83=1,IF(J83=1,0,1),0) -> 0 | L83: 0 | M83: =IF(I83=1,IF(L83=1,0,1),0) -> 0 | N83: 0 | O83: =IF(I83=1,IF(N83=1,0,1),0) -> 0 | P83: 0 | Q83: 0 | R83: 0 | S83: 0 | T83: 0 | V83: 84 | W83: 0.58428629
A84: 0115101 | B84: Aceite de soya | C84: Articulo | D84: Alimentos y Bebidas No Alcohólicas | E84: 0 | F84: 0 | G84: 0 | H84: 0 | I84: 1 | J84: 1 | K84: =IF(I84=1,IF(J84=1,0,1),0) -> 0 | L84: 1 | M84: =IF(I84=1,IF(L84=1,0,1),0) -> 0 | N84: 1 | O84: =IF(I84=1,IF(N84=1,0,1),0) -> 0 | P84: 1 | Q84: 0 | R84: 0 | S84: 0 | T84: 0 | U84: IPC_059 | V84: 85 | W84: 0.55307219
A85: 0115104 | B85: Aceite puro de origen vegetal | C85: Articulo | D85: Alimentos y Bebidas No Alcohólicas | E85: 0 | F85: 0 | G85: 0 | H85: 0 | I85: 1 | J85: 1 | K85: =IF(I85=1,IF(J85=1,0,1),0) -> 0 | L85: 1 | M85: =IF(I85=1,IF(L85=1,0,1),0) -> 0 | N85: 1 | O85: =IF(I85=1,IF(N85=1,0,1),0) -> 0 | P85: 1 | Q85: 0 | R85: 0 | S85: 0 | T85: 1 | U85: IPC_060 | V85: 86 | W85: 0.031214098
A86: 01152 | B86: Margarina y mantequilla | C86: SubClase | D86: Alimentos y Bebidas No Alcohólicas | E86: 0 | F86: 0 | G86: 0 | H86: 1 | I86: 0 | J86: 0 | K86: =IF(I86=1,IF(J86=1,0,1),0) -> 0 | L86: 0 | M86: =IF(I86=1,IF(L86=1,0,1),0) -> 0 | N86: 0 | O86: =IF(I86=1,IF(N86=1,0,1),0) -> 0 | P86: 0 | Q86: 0 | R86: 0 | S86: 0 | T86: 0 | V86: 87 | W86: 0.074831744
A87: 0115202 | B87: Margarina | C87: Articulo | D87: Alimentos y Bebidas No Alcohólicas | E87: 0 | F87: 0 | G87: 0 | H87: 0 | I87: 1 | J87: 1 | K87: =IF(I87=1,IF(J87=1,0,1),0) -> 0 | L87: 1 | M87: =IF(I87=1,IF(L87=1,0,1),0) -> 0 | N87: 1 | O87: =IF(I87=1,IF(N87=1,0,1),0) -> 0 | P87: 1 | Q87: 0 | R87: 0 | S87: 0 | T87: 0 | U87: IPC_061 | V87: 88 | W87: 0.074831744
A88: 0116 | B88: Frutas | C88: Clase | D88: Alimentos y Bebidas No Alcohólicas | E88: 0 | F88: 0 | G88: 1 | H88: 0 | I88: 0 | J88: 0 | K88: =IF(I88=1,IF(J88=1,0,1),0) -> 0 | L88: 0 | M88: =IF(I88=1,IF(L88=1,0,1),0) -> 0 | N88: 0 | O88: =IF(I88=1,IF(N88=1,0,1),0) -> 0 | P88: 0 | Q88: 0 | R88: 0 | S88: 0 | T88: 0 | V88: 89 | W88: 2.1186847
A89: 01161 | B89: Frutas frescas | C89: SubClase | D89: Alimentos y Bebidas No Alcohólicas | E89: 0 | F89: 0 | G89: 0 | H89: 1 | I89: 0 | J89: 0 | K89: =IF(I89=1,IF(J89=1,0,1),0) -> 0 | L89: 0 | M89: =IF(I89=1,IF(L89=1,0,1),0) -> 0 | N89: 0 | O89: =IF(I89=1,IF(N89=1,0,1),0) -> 0 | P89: 0 | Q89: 0 | R89: 0 | S89: 0 | T89: 0 | V89: 90 | W89: 2.0374588
A90: 0116101 | B90: Plátano verde | C90: Articulo | D90: Alimentos y Bebidas No Alcohólicas | E90: 0 | F90: 0 | G90: 0 | H90: 0 | I90: 1 | J90: 0 | K90: =IF(I90=1,IF(J90=1,0,1),0) -> 1 | L90: 1 | M90: =IF(I90=1,IF(L90=1,0,1),0) -> 0 | N90: 1 | O90: =IF(I90=1,IF(N90=1,0,1),0) -> 0 | P90: 1 | Q90: 0 | R90: 0 | S90: 0 | T90: 0 | U90: IPC_062 | V90: 91 | W90: 0.80309174
A91: 0116102 | B91: Guineo verde | C91: Articulo | D91: Alimentos y Bebidas No Alcohólicas | E91: 0 | F91: 0 | G91: 0 | H91: 0 | I91: 1 | J91: 0 | K91: =IF(I91=1,IF(J91=1,0,1),0) -> 1 | L91: 1 | M91: =IF(I91=1,IF(L91=1,0,1),0) -> 0 | N91: 1 | O91: =IF(I91=1,IF(N91=1,0,1),0) -> 0 | P91: 1 | Q91: 0 | R91: 0 | S91: 0 | T91: 0 | U91: IPC_063 | V91: 92 | W91: 0.37426094
A92: 0116103 | B92: Aguacate | C92: Articulo | D92: Alimentos y Bebidas No Alcohólicas | E92: 0 | F92: 0 | G92: 0 | H92: 0 | I92: 1 | J92: 0 | K92: =IF(I92=1,IF(J92=1,0,1),0) -> 1 | L92: 1 | M92: =IF(I92=1,IF(L92=1,0,1),0) -> 0 | N92: 1 | O92: =IF(I92=1,IF(N92=1,0,1),0) -> 0 | P92: 1 | Q92: 0 | R92: 0 | S92: 0 | T92: 0 | U92: IPC_064 | V92: 93 | W92: 0.13843747
A93: 0116104 | B93: Plátano maduro | C93: Articulo | D93: Alimentos y Bebidas No Alcohólicas | E93: 0 | F93: 0 | G93: 0 | H93: 0 | I93: 1 | J93: 0 | K93: =IF(I93=1,IF(J93=1,0,1),0) -> 1 | L93: 0 | M93: =IF(I93=1,IF(L93=1,0,1),0) -> 1 | N93: 1 | O93: =IF(I93=1,IF(N93=1,0,1),0) -> 0 | P93: 1 | Q93: 0 | R93: 0 | S93: 0 | T93: 0 | U93: IPC_065 | V93: 94 | W93: 0.1753031
A94: 0116105 | B94: Lechoza | C94: Articulo | D94: Alimentos y Bebidas No Alcohólicas | E94: 0 | F94: 0 | G94: 0 | H94: 0 | I94: 1 | J94: 0 | K94: =IF(I94=1,IF(J94=1,0,1),0) -> 1 | L94: 1 | M94: =IF(I94=1,IF(L94=1,0,1),0) -> 0 | N94: 1 | O94: =IF(I94=1,IF(N94=1,0,1),0) -> 0 | P94: 1 | Q94: 0 | R94: 0 | S94: 0 | T94: 0 | U94: IPC_066 | V94: 95 | W94: 0.071448493
A95: 0116106 | B95: Naranjas | C95: Articulo | D95: Alimentos y Bebidas No Alcohólicas | E95: 0 | F95: 0 | G95: 0 | H95: 0 | I95: 1 | J95: 0 | K95: =IF(I95=1,IF(J95=1,0,1),0) -> 1 | L95: 1 | M95: =IF(I95=1,IF(L95=1,0,1),0) -> 0 | N95: 1 | O95: =IF(I95=1,IF(N95=1,0,1),0) -> 0 | P95: 1 | Q95: 0 | R95: 0 | S95: 0 | T95: 0 | U95: IPC_067 | V95: 96 | W95: 0.064108323
A96: 0116107 | B96: Limón agrio | C96: Articulo | D96: Alimentos y Bebidas No Alcohólicas | E96: 0 | F96: 0 | G96: 0 | H96: 0 | I96: 1 | J96: 0 | K96: =IF(I96=1,IF(J96=1,0,1),0) -> 1 | L96: 1 | M96: =IF(I96=1,IF(L96=1,0,1),0) -> 0 | N96: 1 | O96: =IF(I96=1,IF(N96=1,0,1),0) -> 0 | P96: 1 | Q96: 0 | R96: 0 | S96: 0 | T96: 0 | U96: IPC_068 | V96: 97 | W96: 0.073570547
A97: 0116108 | B97: Guineo maduro | C97: Articulo | D97: Alimentos y Bebidas No Alcohólicas | E97: 0 | F97: 0 | G97: 0 | H97: 0 | I97: 1 | J97: 0 | K97: =IF(I97=1,IF(J97=1,0,1),0) -> 1 | L97: 1 | M97: =IF(I97=1,IF(L97=1,0,1),0) -> 0 | N97: 1 | O97: =IF(I97=1,IF(N97=1,0,1),0) -> 0 | P97: 1 | Q97: 0 | R97: 0 | S97: 0 | T97: 0 | U97: IPC_069 | V97: 98 | W97: 0.062554214
A98: 0116109 | B98: Piña | C98: Articulo | D98: Alimentos y Bebidas No Alcohólicas | E98: 0 | F98: 0 | G98: 0 | H98: 0 | I98: 1 | J98: 0 | K98: =IF(I98=1,IF(J98=1,0,1),0) -> 1 | L98: 1 | M98: =IF(I98=1,IF(L98=1,0,1),0) -> 0 | N98: 1 | O98: =IF(I98=1,IF(N98=1,0,1),0) -> 0 | P98: 1 | Q98: 0 | R98: 0 | S98: 0 | T98: 0 | U98: IPC_070 | V98: 99 | W98: 0.094719724
A99: 0116110 | B99: Manzanas | C99: Articulo | D99: Alimentos y Bebidas No Alcohólicas | E99: 0 | F99: 0 | G99: 0 | H99: 0 | I99: 1 | J99: 1 | K99: =IF(I99=1,IF(J99=1,0,1),0) -> 0 | L99: 1 | M99: =IF(I99=1,IF(L99=1,0,1),0) -> 0 | N99: 1 | O99: =IF(I99=1,IF(N99=1,0,1),0) -> 0 | P99: 1 | Q99: 0 | R99: 0 | S99: 0 | T99: 0 | U99: IPC_071 | V99: 100 | W99: 0.087658117
A100: 0116112 | B100: Chinola | C100: Articulo | D100: Alimentos y Bebidas No Alcohólicas | E100: 0 | F100: 0 | G100: 0 | H100: 0 | I100: 1 | J100: 0 | K100: =IF(I100=1,IF(J100=1,0,1),0) -> 1 | L100: 1 | M100: =IF(I100=1,IF(L100=1,0,1),0) -> 0 | N100: 1 | O100: =IF(I100=1,IF(N100=1,0,1),0) -> 0 | P100: 1 | Q100: 0 | R100: 0 | S100: 0 | T100: 0 | U100: IPC_072 | V100: 101 | W100: 0.052979396
...

Sheet comprobacion_codes
A1: id | B1: From online file | C1: Original | D1: Iguales
A2: 1 | B2: Alimentos y Bebidas No Alcohólicas | C2: =dummys!B2 -> Alimentos y Bebidas No Alcohólicas | D2: =C2=B2 -> TRUE
A3: 11 | B3: Alimentos | C3: =dummys!B3 -> Alimentos | D3: =C3=B3 -> TRUE
A4: 111 | B4: Pan y cereales | C4: =dummys!B4 -> Pan y cereales | D4: =C4=B4 -> TRUE
A5: 1111 | B5: Pan | C5: =dummys!B5 -> Pan | D5: =C5=B5 -> TRUE
A6: 111101 | B6: Pan sobado | C6: =dummys!B6 -> Pan sobado | D6: =C6=B6 -> TRUE
A7: 111102 | B7: Pan de agua | C7: =dummys!B7 -> Pan de agua | D7: =C7=B7 -> TRUE
A8: 111104 | B8: Pan Integral | C8: =dummys!B8 -> Pan Integral | D8: =C8=B8 -> TRUE
A9: 1112 | B9: Galletas y productos de panadería | C9: =dummys!B9 -> Galletas y productos de panadería | D9: =C9=B9 -> TRUE
A10: 111201 | B10: Galletas saladas | C10: =dummys!B10 -> Galletas saladas | D10: =C10=B10 -> TRUE
A11: 111202 | B11: Bizcochos | C11: =dummys!B11 -> Bizcochos | D11: =C11=B11 -> TRUE
A12: 111203 | B12: Galletas dulces | C12: =dummys!B12 -> Galletas dulces | D12: =C12=B12 -> TRUE
A13: 111204 | B13: Galletas de harina | C13: =dummys!B13 -> Galletas de harina | D13: =C13=B13 -> TRUE
... A612: 1271105 | B612: Trámite para pasaporte (renovación) | C612: =dummys!B612 -> Trámite para pasaporte (renovación) | D612: =C612=B612 -> TRUE
A613: Z0001 | B613: Indice General | C613: =dummys!B613 -> Indice General | D613: =C613=B613 -> TRUE
